_azureeye
_hardware
azure
